[{"id":72,"name":"Alguém lhe recomendou usar o serviço de aviso anônimo","lang_key":"pt-br","active":true},{"id":78,"name":"Eu cei qui vose eh da paliosa","lang_key":"pt-br","active":true},{"id":69,"name":"Eu sei que você peidou","lang_key":"pt-br","active":true},{"id":13,"name":"Mas que mesa bagunçada hein","lang_key":"pt-br","active":true},{"id":83,"name":"Não é seu aniversário, mas você tá de parabéns ;)","lang_key":"pt-br","active":true},{"id":66,"name":"Não gostei da sua atitude","lang_key":"pt-br","active":true},{"id":8,"name":"O barulho dos pés e/ou mãos incomodam","lang_key":"pt-br","active":true},{"id":5,"name":"O seu vaso sanitário está sujo de cocô","lang_key":"pt-br","active":true},{"id":15,"name":"Relaxa, você está muito estressado(a)","lang_key":"pt-br","active":true},{"id":14,"name":"Sou um(a) admirador(a) secreto(a)","lang_key":"pt-br","active":true},{"id":4,"name":"Sua menstruação manchou sua roupa","lang_key":"pt-br","active":true},{"id":57,"name":"Te acho muito metido(a)","lang_key":"pt-br","active":true},{"id":11,"name":"Teu cofrinho tá aparecendo","lang_key":"pt-br","active":true},{"id":17,"name":"Teu som tá muito alto. Poderia diminuir por favor?","lang_key":"pt-br","active":true},{"id":10,"name":"Tua roupa tá do lado avesso","lang_key":"pt-br","active":true},{"id":75,"name":"Você é um péssimo motorista, pelo menos aprenda a estacionar direito","lang_key":"pt-br","active":true},{"id":1,"name":"Você está com mau hálito","lang_key":"pt-br","active":true},{"id":16,"name":"Você está com o ziper aberto","lang_key":"pt-br","active":true},{"id":2,"name":"Você está com odor de suor","lang_key":"pt-br","active":true},{"id":7,"name":"Você está fazendo um barulho irritante com a boca","lang_key":"pt-br","active":true},{"id":63,"name":"Você não é um bom chefe","lang_key":"pt-br","active":true},{"id":82,"name":"Você reclama demais","lang_key":"pt-br","active":true},{"id":79,"name":"Você tá com ramela nos olhos","lang_key":"pt-br","active":true},{"id":9,"name":"Você tá com um chulezinho hein","lang_key":"pt-br","active":true},{"id":18,"name":"Você tá muito linda, tá judiando do meu coração","lang_key":"pt-br","active":true},{"id":19,"name":"Você tá um gato, to de olho hein, se liga","lang_key":"pt-br","active":true},{"id":12,"name":"Você tem caca no nariz","lang_key":"pt-br","active":true},{"id":3,"name":"Você tem sujeira nos dentes","lang_key":"pt-br","active":true},{"id":60,"name":"Você tem um odiador(a) secreto(a)","lang_key":"pt-br","active":true},{"id":25,"name":"Do you really need to eat so loud?","lang_key":"en","active":true},{"id":29,"name":"Do you really need to show your butt crack to everybody?","lang_key":"en","active":true},{"id":26,"name":"Does your hands and/or feet really need to be this loud?","lang_key":"en","active":true},{"id":90,"name":"I cant take my eyes off of you beautiful!","lang_key":"en","active":true},{"id":37,"name":"I cant take my eyes off of you handsome!","lang_key":"en","active":true},{"id":67,"name":"I dont like your attitude","lang_key":"en","active":true},{"id":70,"name":"I know you have farted","lang_key":"en","active":true},{"id":73,"name":"I recommend this anonymous warning service to you","lang_key":"en","active":true},{"id":86,"name":"It is not your birthday, congratulations though. you are hot ;)","lang_key":"en","active":true},{"id":56,"name":"Please respect, no whistle","lang_key":"en","active":true},{"id":88,"name":"There is only one thing missing in you. myself","lang_key":"en","active":true},{"id":33,"name":"Wow, you are too stressed, try to chill out","lang_key":"en","active":true},{"id":64,"name":"You are not a good boss","lang_key":"en","active":true},{"id":58,"name":"You are so full of yourself","lang_key":"en","active":true},{"id":36,"name":"You are so hot you hurt my heart, you are beautiful","lang_key":"en","active":true},{"id":76,"name":"You are such a terrible driver, you should at least learn how to park","lang_key":"en","active":true},{"id":84,"name":"You complain too much","lang_key":"en","active":true},{"id":80,"name":"You got some sleep in your eyes","lang_key":"en","active":true},{"id":30,"name":"You have a booger in your nose","lang_key":"en","active":true},{"id":32,"name":"You have a secret admirer, me =D","lang_key":"en","active":true},{"id":22,"name":"You have got something stuck on your teeth","lang_key":"en","active":true},{"id":24,"name":"You have some smelly shit stuck in your toilet","lang_key":"en","active":true},{"id":20,"name":"Your bad breath is bothering me","lang_key":"en","active":true},{"id":28,"name":"Your clothes are inside out","lang_key":"en","active":true},{"id":31,"name":"Your desk is a complete mess","lang_key":"en","active":true},{"id":27,"name":"Your feet are really smelly","lang_key":"en","active":true},{"id":23,"name":"Your flow leaked in your clothes","lang_key":"en","active":true},{"id":35,"name":"Your music/sound is too loud. Please turn it down","lang_key":"en","active":true},{"id":21,"name":"Your sweat odor bothers","lang_key":"en","active":true},{"id":34,"name":"Your zipper is down, dont let it run","lang_key":"en","active":true},{"id":55,"name":"!No puedo despegar mis ojos de tí, guapo!","lang_key":"es","active":true},{"id":74,"name":"Álguien te recomienda este servicio de aviso anónimo","lang_key":"es","active":true},{"id":59,"name":"Eres muy presumido","lang_key":"es","active":true},{"id":87,"name":"Eres un angel","lang_key":"es","active":true},{"id":68,"name":"No me gustó tu actitud","lang_key":"es","active":true},{"id":71,"name":"Sé que usted ha tirado un pedo","lang_key":"es","active":true},{"id":53,"name":"Su música/audio es demasiado alto. Por favor, baje el volumen","lang_key":"es","active":true},{"id":39,"name":"Su olor del sudor me molesta","lang_key":"es","active":true},{"id":85,"name":"Te quejas demasiado","lang_key":"es","active":true},{"id":40,"name":"Tiene algo atorado en los dientes","lang_key":"es","active":true},{"id":52,"name":"Tu cremallera está abierta","lang_key":"es","active":true},{"id":49,"name":"Tu escritorio está un desastre","lang_key":"es","active":true},{"id":47,"name":"Tu grieta del extremo está muy visible","lang_key":"es","active":true},{"id":41,"name":"Tu menstruación te manchó la ropa","lang_key":"es","active":true},{"id":48,"name":"Tu tiene un notable mocos en la nariz","lang_key":"es","active":true},{"id":54,"name":"Usted es tan caliente que daño a mi corazón, eres muy hermosa","lang_key":"es","active":true},{"id":77,"name":"Usted es un pésimo conductor, aprender a aparcar","lang_key":"es","active":true},{"id":46,"name":"Usted está con la ropa al revés","lang_key":"es","active":true},{"id":38,"name":"Usted está con mal aliento","lang_key":"es","active":true},{"id":43,"name":"Usted está haciendo ruido molesto con la boca","lang_key":"es","active":true},{"id":44,"name":"Usted está haciendo ruido molesto con los pies u manos","lang_key":"es","active":true},{"id":51,"name":"Usted está muy estresado, relajarse","lang_key":"es","active":true},{"id":65,"name":"Usted no es un buen jefe","lang_key":"es","active":true},{"id":45,"name":"Usted tiene mal olor en los pies","lang_key":"es","active":true},{"id":42,"name":"Usted tiene mierda pegado en su sanitário","lang_key":"es","active":true},{"id":81,"name":"Usted tiene reuma en tus ojos","lang_key":"es","active":true},{"id":50,"name":"Usted tiene un admirador secreto","lang_key":"es","active":true},{"id":89,"name":"¿Te puedo invitar a una cubata?","lang_key":"es","active":true}]
